_glmnet.cpython-39-darwin.so
dropkick/__init__.py
dropkick/__main__.py
dropkick/_version.py
dropkick/api.py
dropkick/errors.py
dropkick/logistic.py
dropkick/qc.py
dropkick/scorer.py
dropkick/util.py
dropkick-1.2.7.dist-info/LICENSE
dropkick-1.2.7.dist-info/METADATA
dropkick-1.2.7.dist-info/WHEEL
dropkick-1.2.7.dist-info/entry_points.txt
dropkick-1.2.7.dist-info/top_level.txt
dropkick-1.2.7.dist-info/RECORD
