Metadata-Version: 2.1
Name: dropkick
Version: 1.2.7
Summary: Automated scRNA-seq filtering
Home-page: https://github.com/KenLauLab/dropkick
Author: Cody Heiser
Author-email: codyheiser49@gmail.com
License: UNKNOWN
Platform: UNKNOWN
Classifier: Programming Language :: Python :: 3
Classifier: Operating System :: OS Independent
Classifier: Intended Audience :: Developers
Classifier: Intended Audience :: Science/Research
Classifier: License :: OSI Approved :: MIT License
Classifier: Topic :: Scientific/Engineering
Requires-Python: >=3.6
Requires-Dist: numpy (>=1.9.2)
Requires-Dist: scipy (>=0.14.1)
Requires-Dist: pandas
Requires-Dist: scikit-learn (>=0.18.0)
Requires-Dist: scikit-image
Requires-Dist: matplotlib (>=3.0.3)
Requires-Dist: scanpy
